{
  "interactionModel": {
    "languageModel": {
      "invocationName": "shabbat ivrit",
      "intents": [
        {
          "name": "PlayRadio",
          "samples": [
            "to play",
            "to start playing",
            "start broadcasting",
            "start streaming"
          ]
        },
        {
          "name": "AMAZON.PauseIntent",
          "samples": []
        },
        {
          "name": "AMAZON.ResumeIntent",
          "samples": []
        },
        {
          "name": "AMAZON.NextIntent",
          "samples": []
        },
        {
          "name": "AMAZON.PreviousIntent",
          "samples": []
        },
        {
          "name": "AMAZON.HelpIntent",
          "samples": []
        },
        {
          "name": "AMAZON.StopIntent",
          "samples": []
        },
        {
          "name": "AMAZON.CancelIntent",
          "samples": []
        },
        {
          "name": "AMAZON.StartOverIntent",
          "samples": []
        }
      ]
    }
  }
}
